langchain_financial/__init__.py
langchain_financial/example_usage.py
langchain_financial/filtering.py
langchain_financial/fusion.py
langchain_financial/hybrid_financial.py
langchain_financial/preprocessing.py
langchain_financial-0.1.1.dist-info/METADATA
langchain_financial-0.1.1.dist-info/WHEEL
langchain_financial-0.1.1.dist-info/RECORD
