Metadata-Version: 2.4
Name: langchain-financial
Version: 0.1.1
Summary: Hybrid financial document retriever for LangChain with RRF fusion and metadata filtering
Project-URL: Homepage, https://github.com/siri1404/langchain-financial
Project-URL: Repository, https://github.com/siri1404/langchain-financial
Project-URL: Documentation, https://github.com/siri1404/langchain-financial#readme
Project-URL: Bug Tracker, https://github.com/siri1404/langchain-financial/issues
Author-email: LangChain Financial Team <financial@langchain.com>
License: MIT
Keywords: financial,fusion,hybrid,langchain,retriever,rrf
Classifier: Development Status :: 4 - Beta
Classifier: Intended Audience :: Developers
Classifier: License :: OSI Approved :: MIT License
Classifier: Programming Language :: Python :: 3
Classifier: Programming Language :: Python :: 3.9
Classifier: Programming Language :: Python :: 3.10
Classifier: Programming Language :: Python :: 3.11
Classifier: Programming Language :: Python :: 3.12
Classifier: Topic :: Scientific/Engineering :: Artificial Intelligence
Classifier: Topic :: Software Development :: Libraries :: Python Modules
Requires-Python: <4.0.0,>=3.9.0
Requires-Dist: langchain-core<1.0.0,>=0.3.0
Requires-Dist: numpy<2.0.0,>=1.21.0
Requires-Dist: pydantic<3.0.0,>=2.0.0
Requires-Dist: rank-bm25<1.0.0,>=0.2.2
Provides-Extra: dev
Requires-Dist: black>=23.0.0; extra == 'dev'
Requires-Dist: flake8>=6.0.0; extra == 'dev'
Requires-Dist: isort>=5.12.0; extra == 'dev'
Requires-Dist: mypy>=1.0.0; extra == 'dev'
Requires-Dist: pytest-cov>=4.0.0; extra == 'dev'
Requires-Dist: pytest>=7.0.0; extra == 'dev'
